{
  "recipe": "UD-English-EWT possessor-lemma marginal s-genitive propensity = (s_count + k*p0)/(s_count + of_count + k), k=4.0, p0=corpus base rate; s-genitive = nmod:poss with possessive-clitic case child; of-genitive = nmod with 'of' case child; per lowercased lemma. FROZEN before any model call.",
  "source": "https://raw.githubusercontent.com/UniversalDependencies/UD_English-EWT/master/en_ewt-ud-{train,dev,test}.conllu",
  "license": "CC BY-SA 4.0 (UD English-EWT; LICENSE.txt verified firsthand s218; s168 in scope)",
  "corpus_meta": {
    "files": {
      "en_ewt_train.conllu": {
        "sha256": "d68e06122a702464c613076523d56740f047e5bbe89dd90ec32737e04d952143"
      },
      "en_ewt_dev.conllu": {
        "sha256": "39239e0a60db3ae68f4b7036189f11b6692741d10ff8240dd91f74f2760d90f8"
      },
      "en_ewt_test.conllu": {
        "sha256": "fa024f43dc5da3c5ac02563bc9bd0e974f46cbb1560823976a8f342a37dc494a"
      }
    },
    "total_s_genitive_possessors": 736,
    "total_of_genitive_possessors": 3384,
    "corpus_base_rate_s": 0.1786,
    "pseudocount_k": 4.0
  },
  "per_lemma": {
    "altar": {
      "s_count": 0,
      "of_count": 0,
      "n_genitive": 0,
      "marginal_s_propensity_smoothed": 0.1786
    },
    "assembly": {
      "s_count": 0,
      "of_count": 1,
      "n_genitive": 1,
      "marginal_s_propensity_smoothed": 0.1429
    },
    "bazaar": {
      "s_count": 0,
      "of_count": 0,
      "n_genitive": 0,
      "marginal_s_propensity_smoothed": 0.1786
    },
    "beacon": {
      "s_count": 0,
      "of_count": 0,
      "n_genitive": 0,
      "marginal_s_propensity_smoothed": 0.1786
    },
    "beaver": {
      "s_count": 0,
      "of_count": 0,
      "n_genitive": 0,
      "marginal_s_propensity_smoothed": 0.1786
    },
    "bison": {
      "s_count": 0,
      "of_count": 0,
      "n_genitive": 0,
      "marginal_s_propensity_smoothed": 0.1786
    },
    "board": {
      "s_count": 0,
      "of_count": 4,
      "n_genitive": 4,
      "marginal_s_propensity_smoothed": 0.0893
    },
    "boulder": {
      "s_count": 0,
      "of_count": 0,
      "n_genitive": 0,
      "marginal_s_propensity_smoothed": 0.1786
    },
    "brotherhood": {
      "s_count": 0,
      "of_count": 0,
      "n_genitive": 0,
      "marginal_s_propensity_smoothed": 0.1786
    },
    "buffalo": {
      "s_count": 0,
      "of_count": 0,
      "n_genitive": 0,
      "marginal_s_propensity_smoothed": 0.1786
    },
    "cabinet": {
      "s_count": 0,
      "of_count": 2,
      "n_genitive": 2,
      "marginal_s_propensity_smoothed": 0.1191
    },
    "canyon": {
      "s_count": 0,
      "of_count": 0,
      "n_genitive": 0,
      "marginal_s_propensity_smoothed": 0.1786
    },
    "capacitor": {
      "s_count": 0,
      "of_count": 0,
      "n_genitive": 0,
      "marginal_s_propensity_smoothed": 0.1786
    },
    "citadel": {
      "s_count": 0,
      "of_count": 0,
      "n_genitive": 0,
      "marginal_s_propensity_smoothed": 0.1786
    },
    "clan": {
      "s_count": 0,
      "of_count": 2,
      "n_genitive": 2,
      "marginal_s_propensity_smoothed": 0.1191
    },
    "clergy": {
      "s_count": 0,
      "of_count": 0,
      "n_genitive": 0,
      "marginal_s_propensity_smoothed": 0.1786
    },
    "coalition": {
      "s_count": 0,
      "of_count": 1,
      "n_genitive": 1,
      "marginal_s_propensity_smoothed": 0.1429
    },
    "cobra": {
      "s_count": 0,
      "of_count": 0,
      "n_genitive": 0,
      "marginal_s_propensity_smoothed": 0.1786
    },
    "committee": {
      "s_count": 1,
      "of_count": 2,
      "n_genitive": 3,
      "marginal_s_propensity_smoothed": 0.2449
    },
    "commune": {
      "s_count": 0,
      "of_count": 0,
      "n_genitive": 0,
      "marginal_s_propensity_smoothed": 0.1786
    },
    "corporation": {
      "s_count": 0,
      "of_count": 2,
      "n_genitive": 2,
      "marginal_s_propensity_smoothed": 0.1191
    },
    "cult": {
      "s_count": 0,
      "of_count": 0,
      "n_genitive": 0,
      "marginal_s_propensity_smoothed": 0.1786
    },
    "cyclone": {
      "s_count": 0,
      "of_count": 0,
      "n_genitive": 0,
      "marginal_s_propensity_smoothed": 0.1786
    },
    "cylinder": {
      "s_count": 0,
      "of_count": 0,
      "n_genitive": 0,
      "marginal_s_propensity_smoothed": 0.1786
    },
    "dagger": {
      "s_count": 0,
      "of_count": 0,
      "n_genitive": 0,
      "marginal_s_propensity_smoothed": 0.1786
    },
    "dam": {
      "s_count": 0,
      "of_count": 0,
      "n_genitive": 0,
      "marginal_s_propensity_smoothed": 0.1786
    },
    "delegation": {
      "s_count": 0,
      "of_count": 0,
      "n_genitive": 0,
      "marginal_s_propensity_smoothed": 0.1786
    },
    "diamond": {
      "s_count": 0,
      "of_count": 0,
      "n_genitive": 0,
      "marginal_s_propensity_smoothed": 0.1786
    },
    "diaspora": {
      "s_count": 0,
      "of_count": 0,
      "n_genitive": 0,
      "marginal_s_propensity_smoothed": 0.1786
    },
    "donkey": {
      "s_count": 0,
      "of_count": 0,
      "n_genitive": 0,
      "marginal_s_propensity_smoothed": 0.1786
    },
    "drought": {
      "s_count": 0,
      "of_count": 0,
      "n_genitive": 0,
      "marginal_s_propensity_smoothed": 0.1786
    },
    "faction": {
      "s_count": 0,
      "of_count": 0,
      "n_genitive": 0,
      "marginal_s_propensity_smoothed": 0.1786
    },
    "faculty": {
      "s_count": 0,
      "of_count": 0,
      "n_genitive": 0,
      "marginal_s_propensity_smoothed": 0.1786
    },
    "federation": {
      "s_count": 0,
      "of_count": 1,
      "n_genitive": 1,
      "marginal_s_propensity_smoothed": 0.1429
    },
    "gambler": {
      "s_count": 0,
      "of_count": 0,
      "n_genitive": 0,
      "marginal_s_propensity_smoothed": 0.1786
    },
    "gang": {
      "s_count": 0,
      "of_count": 0,
      "n_genitive": 0,
      "marginal_s_propensity_smoothed": 0.1786
    },
    "geyser": {
      "s_count": 0,
      "of_count": 0,
      "n_genitive": 0,
      "marginal_s_propensity_smoothed": 0.1786
    },
    "gravel": {
      "s_count": 0,
      "of_count": 0,
      "n_genitive": 0,
      "marginal_s_propensity_smoothed": 0.1786
    },
    "guild": {
      "s_count": 0,
      "of_count": 1,
      "n_genitive": 1,
      "marginal_s_propensity_smoothed": 0.1429
    },
    "hamster": {
      "s_count": 0,
      "of_count": 0,
      "n_genitive": 0,
      "marginal_s_propensity_smoothed": 0.1786
    },
    "hawk": {
      "s_count": 0,
      "of_count": 0,
      "n_genitive": 0,
      "marginal_s_propensity_smoothed": 0.1786
    },
    "hermit": {
      "s_count": 0,
      "of_count": 0,
      "n_genitive": 0,
      "marginal_s_propensity_smoothed": 0.1786
    },
    "heron": {
      "s_count": 0,
      "of_count": 0,
      "n_genitive": 0,
      "marginal_s_propensity_smoothed": 0.1786
    },
    "horde": {
      "s_count": 0,
      "of_count": 0,
      "n_genitive": 0,
      "marginal_s_propensity_smoothed": 0.1786
    },
    "hunter": {
      "s_count": 0,
      "of_count": 0,
      "n_genitive": 0,
      "marginal_s_propensity_smoothed": 0.1786
    },
    "hurricane": {
      "s_count": 0,
      "of_count": 0,
      "n_genitive": 0,
      "marginal_s_propensity_smoothed": 0.1786
    },
    "iceberg": {
      "s_count": 0,
      "of_count": 1,
      "n_genitive": 1,
      "marginal_s_propensity_smoothed": 0.1429
    },
    "jaguar": {
      "s_count": 0,
      "of_count": 0,
      "n_genitive": 0,
      "marginal_s_propensity_smoothed": 0.1786
    },
    "jockey": {
      "s_count": 0,
      "of_count": 0,
      "n_genitive": 0,
      "marginal_s_propensity_smoothed": 0.1786
    },
    "jury": {
      "s_count": 1,
      "of_count": 0,
      "n_genitive": 1,
      "marginal_s_propensity_smoothed": 0.3429
    },
    "lagoon": {
      "s_count": 0,
      "of_count": 0,
      "n_genitive": 0,
      "marginal_s_propensity_smoothed": 0.1786
    },
    "league": {
      "s_count": 0,
      "of_count": 1,
      "n_genitive": 1,
      "marginal_s_propensity_smoothed": 0.1429
    },
    "legion": {
      "s_count": 0,
      "of_count": 0,
      "n_genitive": 0,
      "marginal_s_propensity_smoothed": 0.1786
    },
    "lizard": {
      "s_count": 0,
      "of_count": 0,
      "n_genitive": 0,
      "marginal_s_propensity_smoothed": 0.1786
    },
    "lobster": {
      "s_count": 0,
      "of_count": 0,
      "n_genitive": 0,
      "marginal_s_propensity_smoothed": 0.1786
    },
    "maiden": {
      "s_count": 0,
      "of_count": 0,
      "n_genitive": 0,
      "marginal_s_propensity_smoothed": 0.1786
    },
    "meteor": {
      "s_count": 0,
      "of_count": 0,
      "n_genitive": 0,
      "marginal_s_propensity_smoothed": 0.1786
    },
    "militia": {
      "s_count": 0,
      "of_count": 0,
      "n_genitive": 0,
      "marginal_s_propensity_smoothed": 0.1786
    },
    "minority": {
      "s_count": 0,
      "of_count": 0,
      "n_genitive": 0,
      "marginal_s_propensity_smoothed": 0.1786
    },
    "mongrel": {
      "s_count": 0,
      "of_count": 0,
      "n_genitive": 0,
      "marginal_s_propensity_smoothed": 0.1786
    },
    "monk": {
      "s_count": 0,
      "of_count": 0,
      "n_genitive": 0,
      "marginal_s_propensity_smoothed": 0.1786
    },
    "monument": {
      "s_count": 0,
      "of_count": 0,
      "n_genitive": 0,
      "marginal_s_propensity_smoothed": 0.1786
    },
    "moon": {
      "s_count": 0,
      "of_count": 0,
      "n_genitive": 0,
      "marginal_s_propensity_smoothed": 0.1786
    },
    "motor": {
      "s_count": 0,
      "of_count": 0,
      "n_genitive": 0,
      "marginal_s_propensity_smoothed": 0.1786
    },
    "nomad": {
      "s_count": 0,
      "of_count": 0,
      "n_genitive": 0,
      "marginal_s_propensity_smoothed": 0.1786
    },
    "otter": {
      "s_count": 0,
      "of_count": 0,
      "n_genitive": 0,
      "marginal_s_propensity_smoothed": 0.1786
    },
    "panel": {
      "s_count": 0,
      "of_count": 1,
      "n_genitive": 1,
      "marginal_s_propensity_smoothed": 0.1429
    },
    "panther": {
      "s_count": 0,
      "of_count": 0,
      "n_genitive": 0,
      "marginal_s_propensity_smoothed": 0.1786
    },
    "parliament": {
      "s_count": 0,
      "of_count": 1,
      "n_genitive": 1,
      "marginal_s_propensity_smoothed": 0.1429
    },
    "pasture": {
      "s_count": 0,
      "of_count": 0,
      "n_genitive": 0,
      "marginal_s_propensity_smoothed": 0.1786
    },
    "peasant": {
      "s_count": 0,
      "of_count": 1,
      "n_genitive": 1,
      "marginal_s_propensity_smoothed": 0.1429
    },
    "pigeon": {
      "s_count": 0,
      "of_count": 1,
      "n_genitive": 1,
      "marginal_s_propensity_smoothed": 0.1429
    },
    "pilot": {
      "s_count": 0,
      "of_count": 3,
      "n_genitive": 3,
      "marginal_s_propensity_smoothed": 0.1021
    },
    "prairie": {
      "s_count": 0,
      "of_count": 0,
      "n_genitive": 0,
      "marginal_s_propensity_smoothed": 0.1786
    },
    "public": {
      "s_count": 0,
      "of_count": 1,
      "n_genitive": 1,
      "marginal_s_propensity_smoothed": 0.1429
    },
    "python": {
      "s_count": 0,
      "of_count": 0,
      "n_genitive": 0,
      "marginal_s_propensity_smoothed": 0.1786
    },
    "rabbit": {
      "s_count": 0,
      "of_count": 0,
      "n_genitive": 0,
      "marginal_s_propensity_smoothed": 0.1786
    },
    "raven": {
      "s_count": 0,
      "of_count": 0,
      "n_genitive": 0,
      "marginal_s_propensity_smoothed": 0.1786
    },
    "ravine": {
      "s_count": 0,
      "of_count": 0,
      "n_genitive": 0,
      "marginal_s_propensity_smoothed": 0.1786
    },
    "rebel": {
      "s_count": 0,
      "of_count": 2,
      "n_genitive": 2,
      "marginal_s_propensity_smoothed": 0.1191
    },
    "rooster": {
      "s_count": 0,
      "of_count": 0,
      "n_genitive": 0,
      "marginal_s_propensity_smoothed": 0.1786
    },
    "rotor": {
      "s_count": 0,
      "of_count": 0,
      "n_genitive": 0,
      "marginal_s_propensity_smoothed": 0.1786
    },
    "sailor": {
      "s_count": 0,
      "of_count": 0,
      "n_genitive": 0,
      "marginal_s_propensity_smoothed": 0.1786
    },
    "sect": {
      "s_count": 0,
      "of_count": 0,
      "n_genitive": 0,
      "marginal_s_propensity_smoothed": 0.1786
    },
    "shepherd": {
      "s_count": 0,
      "of_count": 0,
      "n_genitive": 0,
      "marginal_s_propensity_smoothed": 0.1786
    },
    "sinkhole": {
      "s_count": 0,
      "of_count": 0,
      "n_genitive": 0,
      "marginal_s_propensity_smoothed": 0.1786
    },
    "society": {
      "s_count": 0,
      "of_count": 2,
      "n_genitive": 2,
      "marginal_s_propensity_smoothed": 0.1191
    },
    "sparrow": {
      "s_count": 0,
      "of_count": 0,
      "n_genitive": 0,
      "marginal_s_propensity_smoothed": 0.1786
    },
    "spider": {
      "s_count": 0,
      "of_count": 0,
      "n_genitive": 0,
      "marginal_s_propensity_smoothed": 0.1786
    },
    "spire": {
      "s_count": 0,
      "of_count": 0,
      "n_genitive": 0,
      "marginal_s_propensity_smoothed": 0.1786
    },
    "squadron": {
      "s_count": 0,
      "of_count": 0,
      "n_genitive": 0,
      "marginal_s_propensity_smoothed": 0.1786
    },
    "staff": {
      "s_count": 0,
      "of_count": 13,
      "n_genitive": 13,
      "marginal_s_propensity_smoothed": 0.042
    },
    "stream": {
      "s_count": 0,
      "of_count": 2,
      "n_genitive": 2,
      "marginal_s_propensity_smoothed": 0.1191
    },
    "syndicate": {
      "s_count": 0,
      "of_count": 0,
      "n_genitive": 0,
      "marginal_s_propensity_smoothed": 0.1786
    },
    "team": {
      "s_count": 1,
      "of_count": 3,
      "n_genitive": 4,
      "marginal_s_propensity_smoothed": 0.2143
    },
    "temple": {
      "s_count": 0,
      "of_count": 0,
      "n_genitive": 0,
      "marginal_s_propensity_smoothed": 0.1786
    },
    "throng": {
      "s_count": 0,
      "of_count": 0,
      "n_genitive": 0,
      "marginal_s_propensity_smoothed": 0.1786
    },
    "tide": {
      "s_count": 0,
      "of_count": 0,
      "n_genitive": 0,
      "marginal_s_propensity_smoothed": 0.1786
    },
    "tribunal": {
      "s_count": 0,
      "of_count": 0,
      "n_genitive": 0,
      "marginal_s_propensity_smoothed": 0.1786
    },
    "troupe": {
      "s_count": 0,
      "of_count": 0,
      "n_genitive": 0,
      "marginal_s_propensity_smoothed": 0.1786
    },
    "tundra": {
      "s_count": 0,
      "of_count": 0,
      "n_genitive": 0,
      "marginal_s_propensity_smoothed": 0.1786
    },
    "valley": {
      "s_count": 0,
      "of_count": 0,
      "n_genitive": 0,
      "marginal_s_propensity_smoothed": 0.1786
    },
    "warrior": {
      "s_count": 0,
      "of_count": 0,
      "n_genitive": 0,
      "marginal_s_propensity_smoothed": 0.1786
    },
    "weasel": {
      "s_count": 0,
      "of_count": 0,
      "n_genitive": 0,
      "marginal_s_propensity_smoothed": 0.1786
    },
    "windmill": {
      "s_count": 0,
      "of_count": 0,
      "n_genitive": 0,
      "marginal_s_propensity_smoothed": 0.1786
    },
    "wire": {
      "s_count": 0,
      "of_count": 0,
      "n_genitive": 0,
      "marginal_s_propensity_smoothed": 0.1786
    },
    "wizard": {
      "s_count": 0,
      "of_count": 0,
      "n_genitive": 0,
      "marginal_s_propensity_smoothed": 0.1786
    },
    "woodland": {
      "s_count": 0,
      "of_count": 0,
      "n_genitive": 0,
      "marginal_s_propensity_smoothed": 0.1786
    }
  }
}